django_supportal/__init__.py
django_supportal/admin.py
django_supportal/api/serializers.py
django_supportal/api/views.py
django_supportal/apps.py
django_supportal/celery.py
django_supportal/migrations/0001_initial.py
django_supportal/migrations/0002_alter_chatmessage_message_type.py
django_supportal/migrations/__init__.py
django_supportal/models.py
django_supportal/services/ai_service.py
django_supportal/services/document_processor.py
django_supportal/services/vector_service.py
django_supportal/settings.py
django_supportal/static/django_supportal/css/chat.css
django_supportal/static/django_supportal/js/chat.js
django_supportal/tasks.py
django_supportal/templates/django_supportal/admin_dashboard.html
django_supportal/templates/django_supportal/chat.html
django_supportal/urls.py
django_supportal/websocket/consumers.py
django_supportal/websocket/ws_routes.py
django_supportal-1.0.2.dist-info/LICENSE
django_supportal-1.0.2.dist-info/METADATA
django_supportal-1.0.2.dist-info/WHEEL
django_supportal-1.0.2.dist-info/RECORD
