Metadata-Version: 2.3
Name: django_supportal
Version: 1.0.2
Summary: AI-Powered business support chat system for django
License: MIT
Keywords: django,ai,chat,support,openai,rag
Author: Amin Dehghan Dehnavi
Author-email: amin.dehghandehnavi@gmail.com
Requires-Python: >=3.10,<4.0
Classifier: Development Status :: 4 - Beta
Classifier: Environment :: Web Environment
Classifier: Framework :: Django
Classifier: Framework :: Django :: 4.2
Classifier: Framework :: Django :: 5.0
Classifier: Framework :: Django :: 5.1
Classifier: Intended Audience :: Developers
Classifier: License :: OSI Approved :: MIT License
Classifier: Operating System :: OS Independent
Classifier: Programming Language :: Python :: 3
Classifier: Programming Language :: Python :: 3.10
Classifier: Programming Language :: Python :: 3.11
Classifier: Programming Language :: Python :: 3.12
Classifier: Programming Language :: Python :: 3.13
Classifier: Topic :: Communications :: Chat
Classifier: Topic :: Internet :: WWW/HTTP :: Dynamic Content
Requires-Dist: PyPDF2 (>=3.0.1,<4.0.0)
Requires-Dist: build (>=1.3.0,<2.0.0)
Requires-Dist: celery (>=5.3.0,<6.0.0)
Requires-Dist: channels (>=4.0.0,<5.0.0)
Requires-Dist: channels-redis (>=4.2.0,<5.0.0)
Requires-Dist: django (>=4.2,<5.0)
Requires-Dist: djangorestframework (>=3.14.0,<4.0.0)
Requires-Dist: faiss-cpu (>=1.7.4,<2.0.0)
Requires-Dist: mysqlclient (>=2.2.0,<3.0.0)
Requires-Dist: numpy (>=1.24.0,<2.0.0)
Requires-Dist: openai (>=1.0.0,<2.0.0)
Requires-Dist: python-decouple (>=3.8,<4.0)
Requires-Dist: python-docx (>=1.1.0,<2.0.0)
Requires-Dist: redis (>=5.0.0,<6.0.0)
Requires-Dist: tiktoken (>=0.5.0,<0.6.0)
Project-URL: Homepage, https://github.com/mrsins02/django_supportal
Project-URL: Repository, https://github.com/mrsins02/django_supportal
